flipflop/active_asynch.v
// D Flip-Flop with Asynchronous Active-Low Reset
// rstn : active-low reset
// d   : data input --> for abrupt changes
// clk : clock input
// q   : data output --> depends on clk and rstn


module dff 	( input d,
              input rstn,
              input clk,
              output reg q);

	always @ (posedge clk or negedge rstn)
       if (!rstn)
          q <= 1'b0; // captures 0 right away when rest is presed(when rstm is low)
       else
          q <= d; // captures d at rising edge of clk
endmodule

flipflop/tb_design.v
module tb_dff;
	reg clk;
	reg d;
	reg rstn;
	reg [2:0] delay; // 2-bit delay for random intervals
    wire q;

    dff  dff0 ( .d(d),
                .rstn (rstn),
                .clk (clk),
                .q (q));

    // Generate clock
    // always #10 clk = ~clk;
    initial begin
        clk = 0;
        forever #5 clk = ~clk;
    end // 
    // Testcase
    initial begin
        $dumpfile("tb_dff.vcd");
        $dumpvars(0, tb_dff);

    	clk <= 0;
    	d <= 0;
    	rstn <= 0;

    	#15 d <= 1; // set d before releasing reset
    	#10 rstn <= 1; // release reset
    	for (int i = 0; i < 5; i=i+1) begin
    		delay = $random;
    		#(delay) d <= i; // change d at random intervals
    	end
        $finish;
    end
endmodule

flipflop/tb_dff.vcd
$date
	Sat Dec 27 17:41:05 2025
$end
$version
	Icarus Verilog
$end
$timescale
	1s
$end
$scope module tb_dff $end
$var wire 1 ! q $end
$var reg 1 " clk $end
$var reg 1 # d $end
$var reg 3 $ delay [2:0] $end
$var reg 1 % rstn $end
$scope module dff0 $end
$var wire 1 " clk $end
$var wire 1 # d $end
$var wire 1 % rstn $end
$var reg 1 ! q $end
$upscope $end
$scope begin $ivl_for_loop0 $end
$var integer 32 & i [31:0] $end
$upscope $end
$upscope $end
$enddefinitions $end
$comment Show the parameter values. $end
$dumpall
$end
#0
$dumpvars
b0 &
0%
bx $
0#
0"
0!
$end
#5
1"
#10
0"
#15
1#
1"
#20
0"
#25
1%
1"
b100 $
#29
0#
b1 $
b1 &
#30
1#
b10 &
0"
#31
0#
b11 $
b11 &
#34
1#
b101 $
b100 &
#35
1!
1"
#39
0#
b101 &
